hunahpu/Similarity.py
hunahpu/__init__.py
Hunahpu-0.0.5a0.dist-info/LICENSE
Hunahpu-0.0.5a0.dist-info/METADATA
Hunahpu-0.0.5a0.dist-info/WHEEL
Hunahpu-0.0.5a0.dist-info/top_level.txt
Hunahpu-0.0.5a0.dist-info/RECORD
