Metadata-Version: 2.1
Name: Hunahpu
Version: 0.0.5a0
Summary: Similarity metrics for bibliography
Home-page: https://github.com/colav/Hunahpu
Author: Colav
Author-email: grupocolav@udea.edu.co
License: BSD
License-File: LICENSE
Requires-Dist: nltk >=3.8.1
Requires-Dist: Unidecode ==1.3.7
Requires-Dist: thefuzz >=0.20.0
